odatse/__init__.py
odatse/_info.py
odatse/_initialize.py
odatse/_main.py
odatse/_runner.py
odatse/algorithm/__init__.py
odatse/algorithm/_algorithm.py
odatse/algorithm/bayes.py
odatse/algorithm/exchange.py
odatse/algorithm/mapper_mpi.py
odatse/algorithm/min_search.py
odatse/algorithm/montecarlo.py
odatse/algorithm/pamc.py
odatse/domain/__init__.py
odatse/domain/_domain.py
odatse/domain/meshgrid.py
odatse/domain/region.py
odatse/exception.py
odatse/mpi.py
odatse/solver/__init__.py
odatse/solver/_solver.py
odatse/solver/analytical.py
odatse/solver/function.py
odatse/util/__init__.py
odatse/util/graph.py
odatse/util/limitation.py
odatse/util/logger.py
odatse/util/mapping.py
odatse/util/neighborlist.py
odatse/util/read_matrix.py
odatse/util/resampling.py
odatse/util/separateT.py
odatse/util/toml.py
odat_se-3.0.0.dist-info/METADATA
odat_se-3.0.0.dist-info/WHEEL
odat_se-3.0.0.dist-info/entry_points.txt
odat_se-3.0.0.dist-info/RECORD
