Metadata-Version: 2.1
Name: ODAT-SE
Version: 3.0.0
Summary: Open Data Analysis Tool for Science and Engineering
Home-page: https://github.com/issp-center-dev/ODAT-SE
License: MPL-2.0
Author: 2DMAT developers
Author-email: 2dmat-dev@issp.u-tokyo.ac.jp
Requires-Python: >=3.9
Classifier: License :: OSI Approved
Classifier: Programming Language :: Python :: 3
Classifier: Programming Language :: Python :: 3.9
Classifier: Programming Language :: Python :: 3.10
Classifier: Programming Language :: Python :: 3.11
Classifier: Programming Language :: Python :: 3.12
Classifier: Programming Language :: Python :: 3.13
Provides-Extra: all
Provides-Extra: bayes
Provides-Extra: exchange
Provides-Extra: min-search
Requires-Dist: mpi4py (>=3,<4) ; extra == "exchange" or extra == "all"
Requires-Dist: numpy (>=1.14,<2.0)
Requires-Dist: physbo (>=2.0.0) ; extra == "bayes" or extra == "all"
Requires-Dist: scipy (>=1,<2) ; extra == "min-search" or extra == "all"
Requires-Dist: tomli (>=1.2)
Project-URL: Repository, https://github.com/issp-center-dev/ODAT-SE
